django_ipchecker
