Metadata-Version: 2.1
Name: django-ipchecker
Version: 0.2
Summary: A Django package to check IP addresses.
Home-page: UNKNOWN
Author: Your Name
Author-email: your@email.com
License: UNKNOWN
Platform: UNKNOWN
License-File: LICENSE
